FPSim2/FPSim2.py
FPSim2/__init__.py
FPSim2/FPSim2lib.cpython-311-darwin.so
FPSim2/FPSim2Cuda.py
FPSim2/base.py
FPSim2/io/__init__.py
FPSim2/io/chem.py
FPSim2/io/backends/pytables.py
FPSim2/io/backends/sqla.py
FPSim2/io/backends/__init__.py
FPSim2/io/backends/base.py
FPSim2/contrib/__init__.py
FPSim2/contrib/isim/isim_comp.py
FPSim2/contrib/isim/__init__.py
FPSim2/contrib/isim/utils.py
FPSim2/scripts/create_fpsim2_fp_db.py
FPSim2/scripts/__init__.py
FPSim2/src/utils.cpp
FPSim2/src/wraps.cpp
FPSim2/src/sim.cpp
FPSim2/src/include/popcnt.hpp
FPSim2/src/include/sim.hpp
FPSim2/src/include/result.hpp
FPSim2/src/include/utils.hpp
FPSim2-0.7.3.dist-info/RECORD
FPSim2-0.7.3.dist-info/LICENSE
FPSim2-0.7.3.dist-info/WHEEL
FPSim2-0.7.3.dist-info/entry_points.txt
FPSim2-0.7.3.dist-info/top_level.txt
FPSim2-0.7.3.dist-info/METADATA
