Metadata-Version: 2.2
Name: FPSim2
Version: 0.7.3
Summary: Simple package for fast molecular similarity searching
Author-email: Eloy Félix <eloyfelix@gmail.com>
Maintainer-email: Eloy Félix <eloyfelix@gmail.com>
License: MIT
Project-URL: Homepage, https://github.com/chembl/FPSim2
Classifier: Development Status :: 4 - Beta
Classifier: License :: OSI Approved :: MIT License
Classifier: Programming Language :: Python :: 3.10
Classifier: Programming Language :: Python :: 3.11
Classifier: Programming Language :: Python :: 3.12
Classifier: Programming Language :: Python :: 3.13
Classifier: Topic :: Scientific/Engineering :: Chemistry
Requires-Python: >=3.10
License-File: LICENSE
Requires-Dist: rdkit>=2022.3.3
Requires-Dist: tables>=3.10
Requires-Dist: numpy>=1.14
Requires-Dist: sqlalchemy>=1.4.47
Requires-Dist: scipy
Requires-Dist: tqdm
